HPSocket/HPSocket4C_amd64_64.dll
HPSocket/HPSocket4C_x86_32.dll
HPSocket/HPSocketAPI.py
HPSocket/HPTypeDef.py
HPSocket/TcpPack.py
HPSocket/TcpPull.py
HPSocket/TcpPush.py
HPSocket/__init__.py
HPSocket/helper.py
HPSocket/libhpsocket4c_aarch64_64.so
HPSocket/libhpsocket4c_amd64_64.so
HPSocket/libhpsocket4c_armv7l_32.so
HPSocket/libhpsocket4c_x64.so
HPSocket/multiplatforms.py
HPSocket/pyhpsocket.py
HPSocket-0.9.3.dist-info/DESCRIPTION.rst
HPSocket-0.9.3.dist-info/METADATA
HPSocket-0.9.3.dist-info/RECORD
HPSocket-0.9.3.dist-info/WHEEL
HPSocket-0.9.3.dist-info/metadata.json
HPSocket-0.9.3.dist-info/top_level.txt
