Metadata-Version: 2.0
Name: HPSocket
Version: 0.9.3
Summary: a python binding for HP-Socket 5.1.1
Home-page: https://gitee.com/RonxBulld/HPSocket4Python
Author: RonxBulld
Author-email: UNKNOWN
License: MIT
Keywords: HPSocket,hpsocket,HP-Socket,hp-socket
Platform: any
